stdtest/__init__.py
stdtest/__main__.py
stdtest/combine.py
stdtest/conf.py
stdtest/listener.py
stdtest/logger.py
stdtest/logger2.py
stdtest/new.py
stdtest/run.py
stdtest/testsync.py
stdtest/testsync2.py
stdtest-0.0.1.dist-info/METADATA
stdtest-0.0.1.dist-info/WHEEL
stdtest-0.0.1.dist-info/entry_points.txt
stdtest-0.0.1.dist-info/top_level.txt
stdtest-0.0.1.dist-info/RECORD
